async_aws_ip_rotator-1.0.2.dist-info/licenses/LICENSE
async_ip_rotator/__init__.py
async_ip_rotator/ip_rotator.py
async_aws_ip_rotator-1.0.2.dist-info/METADATA
async_aws_ip_rotator-1.0.2.dist-info/WHEEL
async_aws_ip_rotator-1.0.2.dist-info/top_level.txt
async_aws_ip_rotator-1.0.2.dist-info/RECORD
