Metadata-Version: 2.4
Name: async-aws-ip-rotator
Version: 1.0.2
Summary: Async IP rotation using AWS API Gateway with httpx support
Author: Zahid Hussain
Author-email: zahidhussain.a2l@gmail.com
Classifier: Programming Language :: Python :: 3
Classifier: Programming Language :: Python :: 3.7
Classifier: Programming Language :: Python :: 3.8
Classifier: Programming Language :: Python :: 3.9
Classifier: Programming Language :: Python :: 3.10
Classifier: Operating System :: OS Independent
Classifier: Framework :: AsyncIO
Classifier: Topic :: Internet :: WWW/HTTP
Requires-Python: >=3.7
License-File: LICENSE
Requires-Dist: httpx>=0.24.0
Requires-Dist: aioboto3>=11.0.0
Requires-Dist: boto3
Requires-Dist: botocore
Dynamic: author
Dynamic: author-email
Dynamic: classifier
Dynamic: description
Dynamic: description-content-type
Dynamic: license-file
Dynamic: requires-dist
Dynamic: requires-python
Dynamic: summary
